mothertongues/__init__.py
mothertongues/__main__.py
mothertongues/api.py
mothertongues/cli.py
mothertongues/config/__init__.py
mothertongues/config/models.py
mothertongues/dictionary.py
mothertongues/exceptions.py
mothertongues/parsers/__init__.py
mothertongues/parsers/csv_parser.py
mothertongues/parsers/json_parser.py
mothertongues/parsers/psv_parser.py
mothertongues/parsers/tsv_parser.py
mothertongues/parsers/utils.py
mothertongues/parsers/xlsx_parser.py
mothertongues/processors/__init__.py
mothertongues/processors/index_builder.py
mothertongues/processors/sorter.py
mothertongues/schemas/config.json
mothertongues/schemas/manifest.json
mothertongues/tests/__init__.py
mothertongues/tests/base_test_case.py
mothertongues/tests/data/alphabet.json
mothertongues/tests/data/alphabet.txt
mothertongues/tests/data/alphabet_empty.json
mothertongues/tests/data/alphabet_empty.txt
mothertongues/tests/data/alphabet_with_numbers_numeric.json
mothertongues/tests/data/alphabet_with_numbers_string.json
mothertongues/tests/data/alphabet_with_punctuation.json
mothertongues/tests/data/config_about.json
mothertongues/tests/data/config_csv.json
mothertongues/tests/data/config_csv_multi.json
mothertongues/tests/data/config_custom.json
mothertongues/tests/data/config_data_check.json
mothertongues/tests/data/config_data_search_algs.json
mothertongues/tests/data/config_duplicate.json
mothertongues/tests/data/config_empty.json
mothertongues/tests/data/config_json.json
mothertongues/tests/data/config_minimal.json
mothertongues/tests/data/config_missing_char.json
mothertongues/tests/data/config_missing_fields.json
mothertongues/tests/data/config_psv.json
mothertongues/tests/data/config_transducers.json
mothertongues/tests/data/config_tsv.json
mothertongues/tests/data/config_xlsx.json
mothertongues/tests/data/data.csv
mothertongues/tests/data/data.json
mothertongues/tests/data/data.psv
mothertongues/tests/data/data.tsv
mothertongues/tests/data/data.xlsx
mothertongues/tests/data/data_check.csv
mothertongues-1.0.20250728.dist-info/LICENSE
mothertongues-1.0.20250728.dist-info/METADATA
mothertongues-1.0.20250728.dist-info/WHEEL
mothertongues-1.0.20250728.dist-info/entry_points.txt
mothertongues-1.0.20250728.dist-info/RECORD
