Metadata-Version: 2.1
Name: mothertongues
Version: 1.0.20250728
Summary: 
Author: roedoejet
Author-email: hello@aidanpine.ca
Requires-Python: >=3.8,<4.0
Classifier: Programming Language :: Python :: 3
Classifier: Programming Language :: Python :: 3.8
Classifier: Programming Language :: Python :: 3.9
Classifier: Programming Language :: Python :: 3.10
Classifier: Programming Language :: Python :: 3.11
Classifier: Programming Language :: Python :: 3.12
Requires-Dist: fastapi (>=0.116.1,<0.117.0)
Requires-Dist: gitlint (>=0.19.0,<0.20.0)
Requires-Dist: httpcore (>=1.0.9,<2.0.0)
Requires-Dist: httpx (>=0.28.1,<0.29.0)
Requires-Dist: jsf (>=0.8.0,<0.9.0)
Requires-Dist: jsonpath-ng (>=1.5.3,<2.0.0)
Requires-Dist: jsonpointer (>=2.3,<3.0)
Requires-Dist: loguru (>=0.6.0,<0.7.0)
Requires-Dist: nltk (>=3.8.1,<4.0.0)
Requires-Dist: numpy (>=1.24.4,<2.0.0) ; python_version < "3.12"
Requires-Dist: numpy (>=1.26.4,<2.0.0) ; python_version >= "3.12"
Requires-Dist: openpyxl (>=3.1.2,<4.0.0)
Requires-Dist: pydantic (>=2.4.2,<3.0.0)
Requires-Dist: questionary (>=2.0.0,<3.0.0)
Requires-Dist: rank-bm25 (>=0.2.2,<0.3.0)
Requires-Dist: typer[all] (==0.9.0)
